{
  "version": "7",
  "dialect": "postgresql",
  "entries": [
    {
      "idx": 0,
      "version": "7",
      "when": 1746204697963,
      "tag": "0000_dear_wrecking_crew",
      "breakpoints": true
    },
    {
      "idx": 1,
      "version": "7",
      "when": 1746234975158,
      "tag": "0001_long_mister_sinister",
      "breakpoints": true
    },
    {
      "idx": 2,
      "version": "7",
      "when": 1746235519235,
      "tag": "0002_abandoned_flatman",
      "breakpoints": true
    },
    {
      "idx": 3,
      "version": "7",
      "when": 1746298798722,
      "tag": "0003_ambiguous_rafael_vega",
      "breakpoints": true
    },
    {
      "idx": 4,
      "version": "7",
      "when": 1746298938996,
      "tag": "0004_adorable_landau",
      "breakpoints": true
    },
    {
      "idx": 5,
      "version": "7",
      "when": 1746416997586,
      "tag": "0005_aberrant_ogun",
      "breakpoints": true
    },
    {
      "idx": 6,
      "version": "7",
      "when": 1746691229208,
      "tag": "0006_famous_blue_shield",
      "breakpoints": true
    },
    {
      "idx": 7,
      "version": "7",
      "when": 1746691428619,
      "tag": "0007_young_betty_ross",
      "breakpoints": true
    },
    {
      "idx": 8,
      "version": "7",
      "when": 1746692201353,
      "tag": "0008_flowery_mimic",
      "breakpoints": true
    },
    {
      "idx": 9,
      "version": "7",
      "when": 1746695075936,
      "tag": "0009_chilly_shadowcat",
      "breakpoints": true
    }
  ]
}